qatalyst/__init__.py
qatalyst/available_samplers.csv
qatalyst/client.py
qatalyst/constants.py
qatalyst/data_processing.py
qatalyst/decoders.py
qatalyst/encoders.py
qatalyst/package_info.py
qatalyst/process_clique_data.py
qatalyst/process_community_detection_data.py
qatalyst/process_constraint_data.py
qatalyst/process_graph_data.py
qatalyst/process_params_data.py
qatalyst/process_partition_data.py
qatalyst/process_qubo_data.py
qatalyst/qcore.py
qatalyst/qgraph.py
qatalyst/result.py
qatalyst/utils.py
qatalyst-4.2.17.dist-info/METADATA
qatalyst-4.2.17.dist-info/WHEEL
qatalyst-4.2.17.dist-info/top_level.txt
qatalyst-4.2.17.dist-info/RECORD
