Metadata-Version: 2.1
Name: qatalyst
Version: 4.2.17
Summary: A client package enabling access to QCI's Qatalyst cloud service for sampling constraint and QUBO problems
Home-page: https://www.quantumcomputinginc.com/
Author: Quantum Computing Inc.
Author-email: support@quantumcomputinginc.com
License: Apache 2.0
Platform: UNKNOWN
Classifier: License :: OSI Approved :: Apache Software License
Classifier: Operating System :: OS Independent
Classifier: Programming Language :: Python :: 3.6
Classifier: Programming Language :: Python :: 3.7
Classifier: Programming Language :: Python :: 3.8
Requires-Python: >=3.6
Requires-Dist: networkx (==2.6.3)
Requires-Dist: numpy (==1.21.2)
Requires-Dist: pandas (==1.3.5)
Requires-Dist: pyyaml (==6.0)
Requires-Dist: requests-toolbelt (==0.9.1)
Requires-Dist: requests (==2.22.0)
Requires-Dist: scipy (==1.7.3)
